sqtab/__init__.py
sqtab/ai_sql.py
sqtab/analyzer.py
sqtab/cli.py
sqtab/config.py
sqtab/db.py
sqtab/describe.py
sqtab/exporter.py
sqtab/head.py
sqtab/importer.py
sqtab/logger.py
sqtab/prompt_utils.py
sqtab/prompts/default.md
sqtab-0.2.4.dist-info/licenses/LICENSE
sqtab-0.2.4.dist-info/METADATA
sqtab-0.2.4.dist-info/WHEEL
sqtab-0.2.4.dist-info/entry_points.txt
sqtab-0.2.4.dist-info/top_level.txt
sqtab-0.2.4.dist-info/RECORD
