Metadata-Version: 2.4
Name: sqtab
Version: 0.2.4
Summary: Minimalist SQLite-based CLI tool with AI assistance for working with tabular data.
Author: Goran Janković
License: MIT
Keywords: sqlite,cli,csv,json,data,database,analysis,command-line
Classifier: Development Status :: 3 - Alpha
Classifier: Programming Language :: Python :: 3
Classifier: Environment :: Console
Classifier: Intended Audience :: Developers
Classifier: Topic :: Database
Classifier: Topic :: Utilities
Requires-Python: >=3.10
License-File: LICENSE
Requires-Dist: typer>=0.12
Requires-Dist: rich>=13.0
Requires-Dist: python-dotenv>=1.0
Requires-Dist: openai>=1.3
Requires-Dist: importlib-metadata>=6.0.0
Dynamic: license-file
